MANIFEST.in
README.md
setup.py
airavata/__init__.py
airavata/admin.py
airavata/apps.py
airavata/exceptions.py
airavata/middleware.py
airavata/models.py
airavata/settings.py
airavata/staticfiles_finder.py
airavata/template_loader.py
airavata/urls.py
airavata/utils.py
airavata/views.py
airavata.egg-info/PKG-INFO
airavata.egg-info/SOURCES.txt
airavata.egg-info/dependency_links.txt
airavata.egg-info/requires.txt
airavata.egg-info/top_level.txt
airavata/management/__init__.py
airavata/management/commands/__init__.py
airavata/management/commands/setprimarydomain.py
airavata/migrations/0001_initial.py
airavata/migrations/0002_auto_20150403_1634.py
airavata/migrations/__init__.py
airavata/templatetags/__init__.py
airavata/templatetags/sitestatic.py